cfpylib/__init__.py
cfpylib/pgscore.py
cfpylib/srvcore.py
cfpylib-0.1.2.dist-info/METADATA
cfpylib-0.1.2.dist-info/WHEEL
cfpylib-0.1.2.dist-info/RECORD
