Metadata-Version: 2.4
Name: cfpylib
Version: 0.1.2
Summary: 
Author: sharmauksa
Author-email: sharmaumesh791@gmail.com
Requires-Python: >=3.12
Classifier: Programming Language :: Python :: 3
Classifier: Programming Language :: Python :: 3.12
Classifier: Programming Language :: Python :: 3.13
Classifier: Programming Language :: Python :: 3.14
Requires-Dist: fastapi[standard] (>=0.121.2,<0.122.0)
Requires-Dist: psycopg2 (>=2.9.11,<3.0.0)
Requires-Dist: pydantic-settings (>=2.12.0,<3.0.0)
Requires-Dist: sqlmodel (>=0.0.27,<0.0.28)
